notes_core/__init__.py
notes_core/commons.py
notes_core/config.py
notes_core/connection.py
notes_core/dbservice.py
notes_core/facade.py
notes_core/notes_core.py
notes_core/predicate.py
notes_core/priority.py
notes_core/services.py
notes_core/status.py
notes_core_lib-1.dist-info/METADATA
notes_core_lib-1.dist-info/WHEEL
notes_core_lib-1.dist-info/top_level.txt
notes_core_lib-1.dist-info/RECORD
