Metadata-Version: 2.1
Name: notes-core-lib
Version: 1
Summary: Notes core library
Home-page: UNKNOWN
Author: Dovydas
Author-email: dovydas@gmail.com
License: UNKNOWN
Platform: UNKNOWN
Requires-Dist: psycopg2-binary
